margument/__init__.py
margument/argument.py
margument/arguments.py
margument/file.py
margument/log.py
margument/non_repeatable_settings.py
margument/options.py
margument/reflection.py
margument/repeatable_settings.py
margument/settings.py
margument/settings_processor.py
margument/yaml.py
margument/version/__init__.py
margument/version/progsettings.py
margument-1.1.4.dist-info/LICENSE
margument-1.1.4.dist-info/METADATA
margument-1.1.4.dist-info/WHEEL
margument-1.1.4.dist-info/top_level.txt
margument-1.1.4.dist-info/RECORD
